django_view_generator/__init__.py
django_view_generator/utils.py
django_view_generator/management/__init__.py
django_view_generator/management/commands/__init__.py
django_view_generator/management/commands/generate_views_and_serializers.py
auto_view_generator-0.1.5.dist-info/LICENCE
auto_view_generator-0.1.5.dist-info/METADATA
auto_view_generator-0.1.5.dist-info/WHEEL
auto_view_generator-0.1.5.dist-info/entry_points.txt
auto_view_generator-0.1.5.dist-info/top_level.txt
auto_view_generator-0.1.5.dist-info/RECORD
