Metadata-Version: 2.1
Name: auto-view-generator
Version: 0.1.5
Summary: A Django management command to generate views and serializers based on models.
Home-page: https://github.com/AdarshShukla777/auto_view_generator
Author: Adarsh Shukla
Author-email: adarshukla999@gmail.com
Classifier: Development Status :: 4 - Beta
Classifier: Intended Audience :: Developers
Classifier: License :: OSI Approved :: MIT License
Classifier: Programming Language :: Python :: 3
Classifier: Framework :: Django
License-File: LICENCE
Requires-Dist: django >=3.0
